discord_github_release_notifier-1.0.0.dist-info/METADATA
discord_github_release_notifier-1.0.0.dist-info/RECORD
discord_github_release_notifier-1.0.0.dist-info/WHEEL
discord_github_release_notifier-1.0.0.dist-info/entry_points.txt
discord_github_release_notifier-1.0.0.dist-info/top_level.txt
github_release_notifier/__init__.py
github_release_notifier/cli.py
github_release_notifier/notifier.py
github_release_notifier/parser.py
github_release_notifier/webhook.py
