Metadata-Version: 2.1
Name: discord-github-release-notifier
Version: 1.0.0
Summary: Github Notifier
Home-page: http://github.com/FFY00/diiscord-github-release-notifier/
Author: Filipe LAÍNS
Author-email: filipe.lains@gmail.com
License: MIT
Platform: UNKNOWN
Classifier: Development Status :: 5 - Production/Stable
Classifier: Programming Language :: Python
Classifier: License :: OSI Approved :: MIT License
Classifier: Natural Language :: English
Classifier: Operating System :: OS Independent
Classifier: Programming Language :: Python :: 3
Classifier: Topic :: Communications
Classifier: Topic :: Internet
Classifier: Topic :: Software Development :: Pre-processors
Classifier: Intended Audience :: Developers
Classifier: Topic :: Software Development :: Build Tools
Requires-Python: >=3
Requires-Dist: feedparser
Requires-Dist: requests
Requires-Dist: tomd
